hyperconf/__init__.py
hyperconf/builtins.yaml
hyperconf/config.py
hyperconf/dsl.py
hyperconf/errors.py
hyperconf/mapping.py
hyperconf-0.3.0.dist-info/LICENSE
hyperconf-0.3.0.dist-info/METADATA
hyperconf-0.3.0.dist-info/WHEEL
hyperconf-0.3.0.dist-info/RECORD
