Metadata-Version: 2.1
Name: hyperconf
Version: 0.3.0
Summary: YAML-based configuration library, featuring zero-code validation and parsing.
License: MIT
Author: Radu Chindris
Author-email: radu.chindris@gmail.com
Requires-Python: >=3.8.1,<4.0.0
Classifier: License :: OSI Approved :: MIT License
Classifier: Programming Language :: Python :: 3
Classifier: Programming Language :: Python :: 3.9
Classifier: Programming Language :: Python :: 3.10
Classifier: Programming Language :: Python :: 3.11
Requires-Dist: PyYAML (>=6.0,<7.0)
